llama_cpp_http/__init__.py
llama_cpp_http/client/__init__.py
llama_cpp_http/client/langchain_llama_cpp_client.py
llama_cpp_http/client/langchain_llama_cpp_embeddings_client.py
llama_cpp_http/server.py
llama_cpp_http-0.3.3.dist-info/LICENSE
llama_cpp_http-0.3.3.dist-info/METADATA
llama_cpp_http-0.3.3.dist-info/WHEEL
llama_cpp_http-0.3.3.dist-info/RECORD
