Metadata-Version: 2.1
Name: llama_cpp_http
Version: 0.3.3
Summary: Python llama.cpp HTTP Server and LangChain LLM Client
Home-page: https://github.com/mtasic85/python-llama-cpp-http
License: MIT
Author: Marko Tasic
Author-email: mtasic85@gmail.com
Requires-Python: >=3.10,<4.0
Classifier: License :: OSI Approved :: MIT License
Classifier: Programming Language :: Python :: 3
Classifier: Programming Language :: Python :: 3.10
Classifier: Programming Language :: Python :: 3.11
Requires-Dist: aiohttp[speedups] (>=3.8.5,<4.0.0)
Requires-Dist: async-timeout (>=4.0.3,<5.0.0)
Requires-Dist: gunicorn (>=21.2.0,<22.0.0)
Requires-Dist: langchain (>=0.0.303,<0.0.304)
Requires-Dist: requests (>=2.31.0,<3.0.0)
Requires-Dist: uvloop (>=0.17.0,<0.18.0)
Requires-Dist: websockets (>=11.0.3,<12.0.0)
Project-URL: Repository, https://github.com/mtasic85/python-llama-cpp-http
